camanager/__init__.py
camanager/__main__.py
camanager/camanager.py
camanager/masterkey.py
camanager/models.py
camanager/utils.py
camanager-0.5.4.dist-info/licenses/LICENSE
camanager-0.5.4.dist-info/METADATA
camanager-0.5.4.dist-info/WHEEL
camanager-0.5.4.dist-info/top_level.txt
camanager-0.5.4.dist-info/RECORD
