Metadata-Version: 2.4
Name: camanager
Version: 0.5.4
Summary: Certificate Authority Manager
Home-page: https://github.com/mneitsabes/camanager
Author: mneitsabes
Classifier: Programming Language :: Python :: 3
Requires-Python: >=3.11
License-File: LICENSE
Requires-Dist: peewee
Requires-Dist: freezegun
Requires-Dist: pycryptodome
Requires-Dist: cryptography
Dynamic: license-file
